PytorchZeroToAll/README.md
PytorchZeroToAll/__init__.py
PytorchZeroToAll/__main__.py
PytorchZeroToAll/file.epub
PytorchZeroToAll/index.html
PytorchZeroToAll/css/__init__.py
PytorchZeroToAll/css/annotations.css
PytorchZeroToAll/css/main.css
PytorchZeroToAll/css/normalize.css
PytorchZeroToAll/css/popup.css
PytorchZeroToAll/font/__init__.py
PytorchZeroToAll/font/fontello.eot
PytorchZeroToAll/font/fontello.svg
PytorchZeroToAll/font/fontello.ttf
PytorchZeroToAll/font/fontello.woff
PytorchZeroToAll/img/__init__.py
PytorchZeroToAll/img/annotator-glyph-sprite.png
PytorchZeroToAll/img/annotator-icon-sprite.png
PytorchZeroToAll/img/apple-touch-icon.png
PytorchZeroToAll/img/cancelfullscreen.png
PytorchZeroToAll/img/close.png
PytorchZeroToAll/img/fullscreen.png
PytorchZeroToAll/img/loader.gif
PytorchZeroToAll/img/menu-icon.png
PytorchZeroToAll/img/save.png
PytorchZeroToAll/img/saved.png
PytorchZeroToAll/img/settings-s.png
PytorchZeroToAll/img/settings.png
PytorchZeroToAll/img/star.png
PytorchZeroToAll/js/__init__.py
PytorchZeroToAll/js/epub.js
PytorchZeroToAll/js/epub.min.js
PytorchZeroToAll/js/epub.min.map
PytorchZeroToAll/js/hooks.min.js
PytorchZeroToAll/js/hooks.min.map
PytorchZeroToAll/js/reader.js
PytorchZeroToAll/js/reader.js.map
PytorchZeroToAll/js/reader.min.js
PytorchZeroToAll/js/reader.min.map
PytorchZeroToAll/js/hooks/__init__.py
PytorchZeroToAll/js/hooks/extensions/__init__.py
PytorchZeroToAll/js/hooks/extensions/highlight.js
PytorchZeroToAll/js/libs/__init__.py
PytorchZeroToAll/js/libs/jquery.min.js
PytorchZeroToAll/js/libs/localforage.min.js
PytorchZeroToAll/js/libs/screenfull.js
PytorchZeroToAll/js/libs/screenfull.min.js
PytorchZeroToAll/js/libs/zip.min.js
PytorchZeroToAll/js/plugins/__init__.py
PytorchZeroToAll/js/plugins/hypothesis.js
PytorchZeroToAll/js/plugins/search.js
pytorch_zero_to_all-2024.3.4.0.dist-info/METADATA
pytorch_zero_to_all-2024.3.4.0.dist-info/WHEEL
pytorch_zero_to_all-2024.3.4.0.dist-info/entry_points.txt
pytorch_zero_to_all-2024.3.4.0.dist-info/top_level.txt
pytorch_zero_to_all-2024.3.4.0.dist-info/RECORD
